{
  "HVIGOR_OHOS_PLUGIN": {
    "MODULES": [
      {
        "MODULE_NAME": "923fe53966c6cd9343e11af776cd4b05be315ea4b200b02e4d5dfb0f929b73bf",
        "API_TYPE": "stageMode",
        "INCLUDE_IN_BUILD": true,
        "IS_COMMAND_LINE_ENTRY_MODULE": false,
        "MODULE_TYPE": "entry",
        "INCREMENTAL_TASKS": {
          "BUILD_NATIVE_WITH_CMAKE": false,
          "COMPILE_ARKTS": false
        },
        "IS_INCREMENTAL_MODULE": false
      }
    ],
    "NATIVE_COMPILER": "Default",
    "IS_FULL_BUILD": true,
    "BUILD_MODE": "debug"
  },
  "HVIGOR": {
    "IS_INCREMENTAL": true,
    "IS_DAEMON": false,
    "IS_PARALLEL": true,
    "IS_HVIGORFILE_TYPE_CHECK": false,
    "TASK_TIME": {
      "923fe53966c6cd9343e11af776cd4b05be315ea4b200b02e4d5dfb0f929b73bf": {
        "clean": 153188800,
        "PreBuild": 89676200,
        "CreateModuleInfo": 665200,
        "GenerateMetadata": 2741100,
        "ConfigureCmake": 7765900,
        "MergeProfile": 3177200,
        "CreateBuildProfile": 1864700,
        "PreCheckSyscap": 404900,
        "GeneratePkgContextInfo": 6701100,
        "ProcessIntegratedHsp": 707500,
        "MakePackInfo": 2409100,
        "ProcessProfile": 70460400,
        "ProcessRouterMap": 3267200,
        "ProcessShareConfig": 2600100,
        "ProcessStartupConfig": 921100,
        "ProcessResource": 3581600,
        "GenerateLoaderJson": 9206400,
        "CompileResource": 147564700,
        "BuildJS": 2096100,
        "SyscapTransform": 1103976800,
        "BuildNativeWithCmake": 2389820200,
        "BuildNativeWithNinja": 165313300,
        "ProcessLibs": 23901800,
        "DoNativeStrip": 53946300,
        "CacheNativeLibs": 4842600,
        "CompileArkTS": 5320112800,
        "GeneratePkgModuleJson": 1680900,
        "ProcessCompiledResources": 308000,
        "PackageHap": 267075600,
        "PackingCheck": 3190900,
        "SignHap": 2008800,
        "CollectDebugSymbol": 762200,
        "assembleHap": 266600
      },
      "APP": {
        "clean": 6508600
      }
    },
    "APIS": [
      "getProperty"
    ],
    "CONFIG_EXPERIMENT": {
      "ENABLE_MODULE_SKIP": false,
      "ENABLE_CPP_FUNCTION_LEVEL_INCREMENTAL": false
    },
    "CONFIG_PROPERTIES": {},
    "BUILD_ID": "202604051757179750",
    "TOTAL_TIME": 8232887800
  }
}